[{"t": "2026-06-22", "score": 100.0, "saturation": 0.0, "n": 15, "suggestions": ["square earrings men", "square earrings gold", "square earrings for women", "square earrings pandora", "square earrings silver", "square earrings diamond", "square earrings big", "square earrings swarovski", "square earrings moissanite", "square earrings hoop", "square earrings black", "square earrings sterling silver", "square earrings with stone", "square earrings with pearl", "square earrings large"], "backend": "google"}, {"t": "2026-06-23", "score": 100.0, "saturation": 0.0, "n": 15, "suggestions": ["square earrings men", "square earrings gold", "square earrings for women", "square earrings pandora", "square earrings silver", "square earrings diamond", "square earrings big", "square earrings swarovski", "square earrings moissanite", "square earrings hoop", "square earrings black", "square earrings sterling silver", "square earrings with stone", "square earrings with pearl", "square earrings large"], "backend": "google"}]